rrtop/__init__.py
rrtop/cli.py
rrtop100-0.1.0.dist-info/DESCRIPTION.rst
rrtop100-0.1.0.dist-info/METADATA
rrtop100-0.1.0.dist-info/RECORD
rrtop100-0.1.0.dist-info/WHEEL
rrtop100-0.1.0.dist-info/entry_points.txt
rrtop100-0.1.0.dist-info/metadata.json
rrtop100-0.1.0.dist-info/top_level.txt
